cheMLearning/__init__.py
cheMLearning/supervised_modelling.py
cheMLearning/unsupervised_modelling.py
cheMLearning/utils.py
cheMLearning-0.0.1.dist-info/LICENSE.txt
cheMLearning-0.0.1.dist-info/METADATA
cheMLearning-0.0.1.dist-info/WHEEL
cheMLearning-0.0.1.dist-info/top_level.txt
cheMLearning-0.0.1.dist-info/RECORD
