Metadata-Version: 2.1
Name: cheMLearning
Version: 0.0.1
Summary: Tools for Metabolomics Multivariate Analysis
Home-page: https://github.com/Christ14n97/cheMLearning
Author: Christian Peralta
Author-email: christian_94_97@hotmail.com
License: MIT
Keywords: metabolomics
Classifier: Development Status :: 4 - Beta
Classifier: Intended Audience :: Education
Classifier: Operating System :: POSIX :: Linux
Classifier: License :: OSI Approved :: MIT License
Classifier: Programming Language :: Python :: 3
License-File: LICENSE.txt
Requires-Dist: numpy (>=1.23.4)
Requires-Dist: pandas (>=1.5.1)
Requires-Dist: plotly (>=5.11.0)
Requires-Dist: scikit-learn (>=1.1.3)
Requires-Dist: scipy (>=1.9.3)
Requires-Dist: xlrd (>=2.0.1)
